nendo_plugin_fx_core/__init__.py
nendo_plugin_fx_core/plugin.py
nendo_plugin_fx_core-0.1.2.dist-info/LICENSE
nendo_plugin_fx_core-0.1.2.dist-info/METADATA
nendo_plugin_fx_core-0.1.2.dist-info/WHEEL
nendo_plugin_fx_core-0.1.2.dist-info/RECORD
