Metadata-Version: 2.1
Name: nendo-plugin-fx-core
Version: 0.1.2
Summary: NendoFX plugin: Use common audio effects out of the box.
Home-page: https://okio.ai
License: GPL-3.0-only
Keywords: nendo,music,audio effect,compressor,reverb,filter,equalizer,distortion,phaser,chorus,filter,eq,digital signal processing,dsp,pedalboard,nendo effects,plugin
Author: Aaron Abebe
Author-email: aaron@okio.ai
Requires-Python: >=3.8,<3.11
Classifier: Development Status :: 5 - Production/Stable
Classifier: Intended Audience :: Developers
Classifier: License :: OSI Approved :: GNU General Public License v3 (GPLv3)
Classifier: Operating System :: OS Independent
Classifier: Programming Language :: Python :: 3
Classifier: Programming Language :: Python :: 3.8
Classifier: Programming Language :: Python :: 3.9
Classifier: Programming Language :: Python :: 3.10
Classifier: Topic :: Multimedia :: Sound/Audio
Requires-Dist: nendo (>=0.2.0,<0.3.0)
Requires-Dist: pedalboard (==0.8.3)
Requires-Dist: pydantic (>=2.0.0,<2.5.0)
Requires-Dist: pydantic-settings (>=2.1.0,<3.0.0)
Project-URL: Repository, https://github.com/okio-ai/nendo_plugin_fx_core
